molecule_containers/__init__.py
molecule_containers/driver.py
molecule_containers/cookiecutter/cookiecutter.json
molecule_containers/cookiecutter/{{cookiecutter.molecule_directory}}/{{cookiecutter.scenario_name}}/converge.yml
molecule_containers/test/__init__.py
molecule_containers/test/test_driver.py
molecule_containers/test/functional/.ansible-lint
molecule_containers/test/functional/__init__.py
molecule_containers/test/functional/conftest.py
molecule_containers/test/functional/test_containers.py
molecule_containers/test/scenarios/driver/containers/molecule/default/converge.yml
molecule_containers/test/scenarios/driver/containers/molecule/default/molecule.yml
molecule_containers-2.0.0.dist-info/LICENSE
molecule_containers-2.0.0.dist-info/METADATA
molecule_containers-2.0.0.dist-info/WHEEL
molecule_containers-2.0.0.dist-info/entry_points.txt
molecule_containers-2.0.0.dist-info/top_level.txt
molecule_containers-2.0.0.dist-info/RECORD
