Metadata-Version: 2.1
Name: molecule-containers
Version: 2.0.0
Summary: Molecule Containers Driver :: run molecule tests on containers
Home-page: https://github.com/ansible-community/molecule-containers
Author: Ansible by Red Hat
Author-email: info@ansible.com
Maintainer: Ansible by Red Hat
Maintainer-email: info@ansible.com
License: MIT
Project-URL: Bug Tracker, https://github.com/ansible-community/molecule-containers/issues
Project-URL: Release Management, https://github.com/ansible-community/molecule-containers/projects
Project-URL: CI: Zuul, https://dashboard.zuul.ansible.com/t/ansible/builds?project=ansible-community/molecule-containers
Project-URL: Source Code, https://github.com/ansible-community/molecule-containers
Keywords: ansible,roles,testing,molecule,plugin,containers,podman,docker
Platform: UNKNOWN
Classifier: Development Status :: 2 - Pre-Alpha
Classifier: Environment :: Console
Classifier: Intended Audience :: Developers
Classifier: Intended Audience :: Information Technology
Classifier: Intended Audience :: System Administrators
Classifier: License :: OSI Approved :: MIT License
Classifier: Natural Language :: English
Classifier: Operating System :: OS Independent
Classifier: Programming Language :: Python :: 3
Classifier: Programming Language :: Python :: 3.8
Classifier: Programming Language :: Python :: 3.9
Classifier: Programming Language :: Python :: 3.10
Classifier: Topic :: System :: Systems Administration
Classifier: Topic :: Utilities
Requires-Python: >=3.8
License-File: LICENSE
Requires-Dist: molecule (>=3.5.0)
Requires-Dist: pyyaml (>=5.1)
Requires-Dist: molecule-docker
Requires-Dist: molecule-podman
Provides-Extra: docker
Requires-Dist: molecule-docker ; extra == 'docker'
Provides-Extra: podman
Requires-Dist: molecule-podman ; extra == 'podman'
